{"name":"searching_by_keyword_apple_should_display_the_corresponding_article","id":"ssvv.features.search.SearchByKeywordStory:searching_by_keyword_apple_should_display_the_corresponding_article","testCaseName":"ssvv.features.search.SearchByKeywordStory","testSteps":[{"number":1,"description":"Is the home page","duration":1825,"startTime":"2022-05-09T20:44:02.359+03:00[Europe/Athens]","screenshots":[{"screenshot":"8f203f1fdaf20d98a030f012e0487428cf4d57a5fac1d0801c870304a4eb1d09.png","timeStamp":1652118242639},{"screenshot":"d6760ca2c53ad9b1fde4801b85e64c4b1e2c08ad6f5b9e1bf52f244840e84312.png","timeStamp":1652118244184}],"result":"SUCCESS","precondition":false,"level":0},{"number":2,"description":"Looks for: apple","duration":5633,"startTime":"2022-05-09T20:44:04.185+03:00[Europe/Athens]","screenshots":[{"screenshot":"dd30483e875acd0ec1655acb504b4c5fc6d200d8350c683d6057b4d4377a7fd2.png","timeStamp":1652118249818}],"result":"SUCCESS","precondition":false,"level":0,"children":[{"number":3,"description":"Enters: apple","duration":585,"startTime":"2022-05-09T20:44:04.187+03:00[Europe/Athens]","screenshots":[{"screenshot":"01d4a5df30a477f602ff27df8e0872445be126e94b094a55bab183cb5a016eb2.png","timeStamp":1652118244772}],"result":"SUCCESS","precondition":false,"level":1},{"number":4,"description":"Starts search","duration":5043,"startTime":"2022-05-09T20:44:04.773+03:00[Europe/Athens]","screenshots":[{"screenshot":"01d4a5df30a477f602ff27df8e0872445be126e94b094a55bab183cb5a016eb2.png","timeStamp":1652118244776},{"screenshot":"dd30483e875acd0ec1655acb504b4c5fc6d200d8350c683d6057b4d4377a7fd2.png","timeStamp":1652118249816}],"result":"SUCCESS","precondition":false,"level":1}]},{"number":5,"description":"Should see definition: A common, round fruit produced by the tree Malus domestica, cultivated in temperate climates.","duration":827,"startTime":"2022-05-09T20:44:09.819+03:00[Europe/Athens]","screenshots":[{"screenshot":"dd30483e875acd0ec1655acb504b4c5fc6d200d8350c683d6057b4d4377a7fd2.png","timeStamp":1652118250646}],"result":"SUCCESS","precondition":false,"level":0}],"userStory":{"id":"ssvv.features.search.SearchByKeywordStory","storyName":"Search by keyword story","storyClassName":"ssvv.features.search.SearchByKeywordStory","path":"search","type":"feature"},"featureTag":{"name":"Search/Search by keyword story","type":"feature","displayName":"Search/Search by keyword story"},"title":"Searching by keyword apple should display the corresponding article","coreIssues":["#WIKI-1"],"tags":[{"name":"Search/Search by keyword story","type":"feature","displayName":"Search by keyword story"},{"name":"Search","type":"capability","displayName":"Search"}],"startTime":"2022-05-09T20:44:02.059+03:00[Europe/Athens]","duration":8587,"projectKey":"","sessionId":"f3996335c2e078946341ca3fded88641","driver":"chrome","isManualTestingUpToDate":false,"manual":false,"testSource":"JUnit","order":0,"result":"SUCCESS","issues":["#WIKI-1"]}